setup.py
my_adi_package/__init__.py
my_adi_package/calculator.py
my_adi_package.egg-info/PKG-INFO
my_adi_package.egg-info/SOURCES.txt
my_adi_package.egg-info/dependency_links.txt
my_adi_package.egg-info/top_level.txt