Metadata-Version: 2.1
Name: my-adi-package
Version: 0.0.1
Summary: ADI python package module
Home-page: https://github.com/vishnubeeram/my_demo_package
Author: vishnu
Author-email: vishnubeeram4@gmail.com
License: UNKNOWN
Platform: UNKNOWN
Classifier: Programming Language :: Python :: 3
Classifier: Operating System :: OS Independent
